{
    "20O(d,d)": {
        "images": [
            "Fits/dd/Outputs/dd_ex.png",
            "Fits/dd/Outputs/ang_0.png",
            "Fits/dd/Outputs/ang_1.png"
        ],
        "links": [
            {
                "url": "https://root.cern/js/latest/?file=http://localhost:8080/currentdir/website/RootFiles/dd.root&status=size&layout=tabs&datex=0.5&optfile=1&title=e796 20O(d,d)",
                "text": "Global fit and angular distributions"
            }
        ]
    },
    "20O(p,p)": {
        "images": [
            "Fits/pp/Outputs/pp_ex.png",
            "Fits/pp/Outputs/effs.png",
            "Fits/pp/Outputs/ang_0.png"
        ],
        "links": [
            {
                "url": "https://root.cern/js/latest/?file=http://localhost:8080/currentdir/website/RootFiles/pp.root&status=size&layout=tabs&datex=0.5&optfile=1&title=e796 20O(p,p)",
                "text": "Global fit and angular distributions"
            }
        ]
    },
    "20O(d,t)": {
        "images": [
            "Fits/dt/Outputs/dt_ex.png",
            "Fits/dt/Outputs/ang_0.png",
            "Fits/dt/Outputs/ang_1.png",
            "Fits/dt/Outputs/ang_2.png",
            "Fits/dt/Outputs/effs.png"
        ],
        "links": [
            {
                "url": "https://root.cern/js/latest/?file=http://localhost:8080/currentdir/website/RootFiles/dt.root&status=size&layout=tabs&datex=0.5&optfile=1&title=e796 20O(d,t)",
                "text": "Global fit and angular distributions"
            }
        ]
    },
    "20O(p,d)": {
        "images": [
            "Fits/pd/Outputs/pd_ex.png",
            "Fits/pd/Outputs/effs.png",
            "Fits/pd/Outputs/ang_0.png"
        ],
        "links": [
            {
                "url": "https://root.cern/js/latest/?file=http://localhost:8080/currentdir/website/RootFiles/pd.root&status=size&layout=tabs&datex=0.5&optfile=1&title=e796 20O(p,d)",
                "text": "Global fit and angular distributions"
            }
        ]
    },
    "Miscellanea": {
        "images": [],
        "links": [
            {
                "url": "https://root.cern/js/latest/",
                "text": "Go to JSRoot"
            },
            {
                "url": "https://root.cern/js/latest/?file=http://localhost:8080/currentdir/website/RootFiles/sigmas.root&status=size&layout=tabs&datex=0.5&optfile=1&title=e796 Miscellanea",
                "text": "Sigma study"
            },
            {
                "url": "https://root.cern/js/latest/?file=http://localhost:8080/currentdir/website/RootFiles/sim_to_ana.root&status=size&layout=tabs&datex=0.5&optfile=1&title=e796 Miscellanea",
                "text": "RP.X() distribution comparison"
            },
            {
                "url": "https://root.cern/js/latest/?file=http://localhost:8080/currentdir/website/RootFiles/emittance.root&status=size&layout=tabs&datex=0.5&optfile=1&title=e796 Miscellanea",
                "text": "Emittance"
            }
        ]
    }
}